README.md
setup.py
csvfilecleaner/clean.py
csvfilecleaner.egg-info/PKG-INFO
csvfilecleaner.egg-info/SOURCES.txt
csvfilecleaner.egg-info/dependency_links.txt
csvfilecleaner.egg-info/not-zip-safe
csvfilecleaner.egg-info/requires.txt
csvfilecleaner.egg-info/top_level.txt