Metadata-Version: 1.0
Name: csvfilecleaner
Version: 0.6
Summary: A very simple utility class for cleaning csv files
Home-page: https://github.com/caleale90/CsvFileCleaner
Author: Alessandro Calefati
Author-email: caleale90@gmail.com
License: MIT
Keywords: csv clean file
Platform: UNKNOWN
